opensearch_client/__init__.py
opensearch_client/async_client.py
opensearch_client/client.py
opensearch_client/exceptions.py
opensearch_client/index.py
opensearch_client/py.typed
opensearch_client/vectorstore.py
opensearch_client/hybrid_search/__init__.py
opensearch_client/hybrid_search/hybrid_query.py
opensearch_client/hybrid_search/pipeline.py
opensearch_client/semantic_search/__init__.py
opensearch_client/semantic_search/knn_search.py
opensearch_client/semantic_search/embeddings/__init__.py
opensearch_client/semantic_search/embeddings/base.py
opensearch_client/semantic_search/embeddings/fastembed.py
opensearch_client/semantic_search/embeddings/openai.py
opensearch_client/text_search/__init__.py
opensearch_client/text_search/analyzer.py
opensearch_client/text_search/query_builder.py
opensearch_client/utils/__init__.py
opensearch_client-0.2.1.dist-info/METADATA
opensearch_client-0.2.1.dist-info/WHEEL
opensearch_client-0.2.1.dist-info/RECORD
