Metadata-Version: 2.4
Name: opensearch-client
Version: 0.2.1
Summary: OpenSearch client with hybrid search support for Korean text
Project-URL: Homepage, https://github.com/namyoungkim/opensearch-client
Project-URL: Repository, https://github.com/namyoungkim/opensearch-client
Author-email: leo <liniarq@gmail.com>
License: MIT
Keywords: hybrid,korean,nori,opensearch,search,vector
Classifier: Development Status :: 3 - Alpha
Classifier: Intended Audience :: Developers
Classifier: License :: OSI Approved :: MIT License
Classifier: Programming Language :: Python :: 3.10
Classifier: Programming Language :: Python :: 3.11
Classifier: Programming Language :: Python :: 3.12
Requires-Python: >=3.10
Requires-Dist: opensearch-py>=3.0.0
Provides-Extra: all
Requires-Dist: aiohttp>=3.0; extra == 'all'
Requires-Dist: fastembed>=0.4; extra == 'all'
Requires-Dist: openai>=1.0; extra == 'all'
Provides-Extra: async
Requires-Dist: aiohttp>=3.0; extra == 'async'
Provides-Extra: local
Requires-Dist: fastembed>=0.4; extra == 'local'
Provides-Extra: openai
Requires-Dist: openai>=1.0; extra == 'openai'
